qtoolkit/__init__.py
qtoolkit/_version.py
qtoolkit/manager.py
qtoolkit/py.typed
qtoolkit/utils.py
qtoolkit/core/__init__.py
qtoolkit/core/base.py
qtoolkit/core/data_objects.py
qtoolkit/core/exceptions.py
qtoolkit/host/__init__.py
qtoolkit/host/base.py
qtoolkit/host/local.py
qtoolkit/host/remote.py
qtoolkit/io/__init__.py
qtoolkit/io/base.py
qtoolkit/io/pbs.py
qtoolkit/io/pbs_base.py
qtoolkit/io/sge.py
qtoolkit/io/shell.py
qtoolkit/io/slurm.py
qtoolkit/io/templates/pbs
qtoolkit/io/templates/sge
qtoolkit/io/templates/shell
qtoolkit/io/templates/slurm
qtoolkit-0.1.7.dist-info/licenses/LICENSE
qtoolkit-0.1.7.dist-info/METADATA
qtoolkit-0.1.7.dist-info/WHEEL
qtoolkit-0.1.7.dist-info/top_level.txt
qtoolkit-0.1.7.dist-info/RECORD
