Metadata-Version: 2.4
Name: qtoolkit
Version: 0.1.7
Summary: QToolKit is a python wrapper interfacing with job queues (e.g. PBS, SLURM, ...).
Author-email: David Waroquiers <david.waroquiers@matgenix.com>
License: modified BSD
Project-URL: homepage, https://matgenix.github.io/qtoolkit/
Project-URL: repository, https://github.com/matgenix/qtoolkit
Project-URL: documentation, https://matgenix.github.io/qtoolkit/
Project-URL: changelog, https://matgenix.github.io/qtoolkit/changelog
Classifier: Development Status :: 5 - Production/Stable
Classifier: Intended Audience :: Information Technology
Classifier: Intended Audience :: Science/Research
Classifier: Intended Audience :: System Administrators
Classifier: Operating System :: OS Independent
Classifier: Programming Language :: Python :: 3
Classifier: Programming Language :: Python :: 3.9
Classifier: Programming Language :: Python :: 3.10
Classifier: Programming Language :: Python :: 3.11
Classifier: Programming Language :: Python :: 3.12
Classifier: Programming Language :: Python :: 3.13
Classifier: Programming Language :: Python :: 3.14
Classifier: Topic :: Other/Nonlisted Topic
Classifier: Topic :: Scientific/Engineering
Requires-Python: >=3.9
License-File: LICENSE
Provides-Extra: dev
Requires-Dist: pre-commit>=3.0.0; extra == "dev"
Provides-Extra: tests
Requires-Dist: pytest-cov<8,>=6; extra == "tests"
Requires-Dist: pytest-mock~=3.14; extra == "tests"
Requires-Dist: pytest<10,>=8; extra == "tests"
Requires-Dist: ruamel.yaml>=0.17; extra == "tests"
Requires-Dist: python-on-whales~=0.75; extra == "tests"
Provides-Extra: maintain
Requires-Dist: git-changelog>=0.6; extra == "maintain"
Provides-Extra: docs
Requires-Dist: ipython!=8.1.0,>=7.0; extra == "docs"
Requires-Dist: matplotlib>=3.3; extra == "docs"
Requires-Dist: pydata-sphinx-theme; extra == "docs"
Requires-Dist: qtoolkit[msonable,remote]; extra == "docs"
Requires-Dist: sphinx>=5; extra == "docs"
Requires-Dist: sphinx-copybutton; extra == "docs"
Requires-Dist: sphinx_design; extra == "docs"
Provides-Extra: strict
Provides-Extra: remote
Requires-Dist: fabric>=3.1.0; extra == "remote"
Provides-Extra: msonable
Requires-Dist: monty>=2023.9.5; extra == "msonable"
Dynamic: license-file
